COPYING
MANIFEST.in
README.rst
buildout.cfg
develop.cfg
requirements.txt
setup.py
version.txt
bob/__init__.py
bob.rppg.base.egg-info/PKG-INFO
bob.rppg.base.egg-info/SOURCES.txt
bob.rppg.base.egg-info/dependency_links.txt
bob.rppg.base.egg-info/entry_points.txt
bob.rppg.base.egg-info/not-zip-safe
bob.rppg.base.egg-info/requires.txt
bob.rppg.base.egg-info/top_level.txt
bob/rppg/__init__.py
bob/rppg/base/__init__.py
bob/rppg/base/utils.py
bob/rppg/base/data/001.face
bob/rppg/base/data/001.jpg
bob/rppg/base/script/__init__.py
bob/rppg/base/script/compute_performance.py
bob/rppg/base/script/frequency_analysis.py
bob/rppg/base/script/test.py
bob/rppg/chrom/__init__.py
bob/rppg/chrom/extract_utils.py
bob/rppg/chrom/script/__init__.py
bob/rppg/chrom/script/extract_pulse.py
bob/rppg/chrom/script/extract_pulse_from_mask.py
bob/rppg/chrom/script/test.py
bob/rppg/cvpr14/__init__.py
bob/rppg/cvpr14/extract_utils.py
bob/rppg/cvpr14/filter_utils.py
bob/rppg/cvpr14/illum_utils.py
bob/rppg/cvpr14/motion_utils.py
bob/rppg/cvpr14/script/__init__.py
bob/rppg/cvpr14/script/extract_face_and_bg_signals.py
bob/rppg/cvpr14/script/filter.py
bob/rppg/cvpr14/script/illumination_rectification.py
bob/rppg/cvpr14/script/motion_elimination.py
bob/rppg/cvpr14/script/test.py
bob/rppg/cvpr14/script/video2skin.py
bob/rppg/ssr/__init__.py
bob/rppg/ssr/ssr_utils.py
bob/rppg/ssr/script/__init__.py
bob/rppg/ssr/script/spatial_subspace_rotation.py
bob/rppg/ssr/script/ssr_from_mask.py
bob/rppg/ssr/script/test.py
doc/conf.py
doc/guide_chrom.rst
doc/guide_cvpr14.rst
doc/guide_performance.rst
doc/guide_ssr.rst
doc/index.rst
doc/py_api_chrom.rst
doc/py_api_cvpr14.rst
doc/py_api_ssr.rst
doc/img/favicon.ico
doc/img/logo.png