Metadata-Version: 1.1
Name: bob.rppg.base
Version: 2.0.6
Summary: Baseline Algorithms for Remote Photoplethysmography (rPPG)
Home-page: https://gitlab.idiap.ch/bob/bob.rppg.base
Author: Guillaume Heusch
Author-email: guillaume.heusch@idiap.ch
License: GPLv3
Keywords: bob,physiological signals,remote photoplethysmography,ppg
Platform: UNKNOWN
Classifier: Framework :: Bob
Classifier: Development Status :: 4 - Beta
Classifier: Intended Audience :: Science/Research
Classifier: License :: OSI Approved :: GNU General Public License v3 (GPLv3)
Classifier: Natural Language :: English
Classifier: Programming Language :: Python
Classifier: Programming Language :: Python :: 3
Classifier: Topic :: Scientific/Engineering :: Artificial Intelligence
Classifier: Topic :: Software Development :: Libraries :: Python Modules
